{
  "timestamp": "2025-04-23 17:17:57",
  "user": "admin_user@clarity-dx.com",
  "filename": "20241217_1280.json",
  "tin": "650003177",
  "rate_type": "create_ota",
  "source": "manual_correction",
  "order_id": "307FB833-31EB-49E1-B18E-072523107DB1",
  "rates": [
    {
      "cpt_code": "73721",
      "rate": 75,
      "modifier": null
    }
  ],
  "ota_data": {
    "provider_name": "Indian River Health Services",
    "provider_npi": "1215989298",
    "provider_type": "",
    "order_id": "307FB833-31EB-49E1-B18E-072523107DB1",
    "notes": ""
  }
}